vetnode/__init__.py
vetnode/__main__.py
vetnode/cli.py
vetnode/configuration.py
vetnode/models.py
vetnode/commands/nvidiasmi/__init__.py
vetnode/commands/nvidiasmi/models.py
vetnode/commands/nvidiasmi/nvidia-smi-info.tfsm
vetnode/commands/nvidiasmi/nvidia_smi_command.py
vetnode/commands/scontrol/__init__.py
vetnode/commands/scontrol/models.py
vetnode/commands/scontrol/scontrol-hostnames.tfsm
vetnode/commands/scontrol/scontrol_command.py
vetnode/evaluations/base_eval.py
vetnode/evaluations/cuda_eval.py
vetnode/evaluations/gpu_eval.py
vetnode/evaluations/internet_access.py
vetnode/evaluations/models.py
vetnode/evaluations/nccl_lib_eval.py
vetnode/evaluations/nccl_pytorch_eval.py
vetnode/evaluations/random.py
vetnode/evaluations/rccl_lib_eval.py
vetnode-0.0.12.dist-info/METADATA
vetnode-0.0.12.dist-info/WHEEL
vetnode-0.0.12.dist-info/entry_points.txt
vetnode-0.0.12.dist-info/licenses/LICENSE
vetnode-0.0.12.dist-info/RECORD
