Metadata-Version: 2.4
Name: VetNode
Version: 0.0.12
Summary: A node vetting cli for Distributed Workloads
Project-URL: Homepage, https://github.com/theely/vetnode
Project-URL: Issues, https://github.com/theely/vetnode/issues
Author-email: Elia Palme <elia.palme@cscs.ch>
License-Expression: BSD-3-Clause
License-File: LICENSE
Classifier: Operating System :: OS Independent
Classifier: Programming Language :: Python :: 3
Requires-Python: >=3.8
Requires-Dist: click
Requires-Dist: pip
Requires-Dist: pydantic
Requires-Dist: pydantic-settings>=2.2.0
Requires-Dist: pydantic-settings[yaml]
Requires-Dist: textfsm
